pytest_beartype/__init__.py
pytest_beartype/py.typed
pytest_beartype-0.1.1.dist-info/LICENSE
pytest_beartype-0.1.1.dist-info/METADATA
pytest_beartype-0.1.1.dist-info/WHEEL
pytest_beartype-0.1.1.dist-info/entry_points.txt
pytest_beartype-0.1.1.dist-info/top_level.txt
pytest_beartype-0.1.1.dist-info/RECORD
