Metadata-Version: 2.1
Name: pytest-beartype
Version: 0.1.1
Summary: Pytest plugin to run your tests with beartype checking enabled.
Author-email: Tushar Sadhwani <tushar.sadhwani000@gmail.com>
License: MIT
Project-URL: Source, https://github.com/tusharsadhwani/pytest-beartype
Classifier: Framework :: Pytest
Classifier: License :: OSI Approved :: MIT License
Classifier: Operating System :: OS Independent
Classifier: Programming Language :: Python :: 3
Classifier: Programming Language :: Python :: 3 :: Only
Classifier: Programming Language :: Python :: 3.8
Classifier: Programming Language :: Python :: 3.9
Classifier: Programming Language :: Python :: 3.10
Classifier: Programming Language :: Python :: 3.11
Classifier: Programming Language :: Python :: 3.12
Classifier: Programming Language :: Python :: Implementation :: CPython
Classifier: Typing :: Typed
Requires-Python: >=3.8
License-File: LICENSE
Requires-Dist: beartype
Requires-Dist: pytest
Provides-Extra: dev
Requires-Dist: black; extra == "dev"
Requires-Dist: mypy; extra == "dev"
Requires-Dist: pytest-cov; extra == "dev"
Requires-Dist: tox; extra == "dev"
